CHANGES.txt
README.txt
bootstrap.py
buildout.cfg
setup.py
src/z3c/__init__.py
src/z3c.boiler.egg-info/PKG-INFO
src/z3c.boiler.egg-info/SOURCES.txt
src/z3c.boiler.egg-info/dependency_links.txt
src/z3c.boiler.egg-info/entry_points.txt
src/z3c.boiler.egg-info/namespace_packages.txt
src/z3c.boiler.egg-info/not-zip-safe
src/z3c.boiler.egg-info/requires.txt
src/z3c.boiler.egg-info/top_level.txt
src/z3c/boiler/README.txt
src/z3c/boiler/__init__.py
src/z3c/boiler/index.txt
src/z3c/boiler/interactive.py
src/z3c/boiler/project-template.xml
src/z3c/boiler/sample-project.xml
src/z3c/boiler/script.py
src/z3c/boiler/tests.py