Metadata-Version: 1.0
Name: z3c.boiler
Version: 0.1.1
Summary: A utility to help jump start Zope 3 projects
Home-page: http://pypi.python.org/pypi/z3c.boiler
Author: Paul Carduner, Stephan Richter, and hopefully others...
Author-email: zope-dev@zope.org
License: ZPL 2.1
Keywords: zope3 project builder boiler
Platform: UNKNOWN
